tektii/__init__.py
tektii/__version__.py
tektii/cli.py
tektii/py.typed
tektii/server.py
tektii/strategy.py
tektii/commands/__init__.py
tektii/commands/analyze.py
tektii/commands/backtest.py
tektii/commands/new.py
tektii/commands/push.py
tektii/commands/serve.py
tektii/commands/validator.py
tektii/models/__init__.py
tektii/models/base.py
tektii/models/broker/__init__.py
tektii/models/broker/conversions.py
tektii/models/broker/errors.py
tektii/models/broker/handlers/__init__.py
tektii/models/broker/handlers/cancel_order.py
tektii/models/broker/handlers/close_position.py
tektii/models/broker/handlers/get_historical_data.py
tektii/models/broker/handlers/get_market_depth.py
tektii/models/broker/handlers/get_risk_metrics.py
tektii/models/broker/handlers/get_state.py
tektii/models/broker/handlers/modify_order.py
tektii/models/broker/handlers/modify_trade_protection.py
tektii/models/broker/handlers/place_order.py
tektii/models/broker/types/account.py
tektii/models/broker/types/broker.py
tektii/models/broker/types/candle.py
tektii/models/broker/types/order.py
tektii/models/broker/types/order_intent.py
tektii/models/broker/types/order_side.py
tektii/models/broker/types/order_status.py
tektii/models/broker/types/order_type.py
tektii/models/broker/types/position.py
tektii/models/broker/types/position_risk.py
tektii/models/broker/types/position_side.py
tektii/models/broker/types/price_level.py
tektii/models/broker/types/protective_orders_on_fill.py
tektii/models/broker/types/stop_limit_order.py
tektii/models/broker/types/stop_order.py
tektii/models/broker/types/time_in_force.py
tektii/models/strategy/__init__.py
tektii/models/strategy/conversions.py
tektii/models/strategy/errors.py
tektii/models/strategy/events/__init__.py
tektii/models/strategy/events/account_update.py
tektii/models/strategy/events/candle_data.py
tektii/models/strategy/events/option_greeks.py
tektii/models/strategy/events/order_update.py
tektii/models/strategy/events/trade_update.py
tektii-1.3.0.dist-info/licenses/LICENSE
tektii-1.3.0.dist-info/METADATA
tektii-1.3.0.dist-info/WHEEL
tektii-1.3.0.dist-info/entry_points.txt
tektii-1.3.0.dist-info/top_level.txt
tektii-1.3.0.dist-info/RECORD
