Metadata-Version: 2.4
Name: tektii
Version: 1.3.0
Summary: Build trading strategies that run anywhere - Write Once. Trade Everywhere.
Author-email: Tektii <support@tektii.com>
Maintainer-email: Tektii Team <support@tektii.com>
License: Apache-2.0
Project-URL: Homepage, https://tektii.com
Project-URL: Documentation, https://docs.tektii.com/sdk
Project-URL: Repository, https://github.com/tektii/tektii-sdk-python
Project-URL: Issues, https://github.com/tektii/tektii-sdk-python/issues
Project-URL: Changelog, https://github.com/tektii/tektii-sdk-python/blob/main/CHANGELOG.md
Keywords: trading,algorithmic-trading,algo-trading,quantitative-finance,finance,fintech,strategy,backtesting,grpc,trading-bot,trading-strategies,market-data,portfolio-management
Classifier: Development Status :: 3 - Alpha
Classifier: Intended Audience :: Developers
Classifier: Intended Audience :: Financial and Insurance Industry
Classifier: Intended Audience :: Science/Research
Classifier: License :: OSI Approved :: Apache Software License
Classifier: Operating System :: OS Independent
Classifier: Programming Language :: Python :: 3
Classifier: Programming Language :: Python :: 3.11
Classifier: Programming Language :: Python :: 3.12
Classifier: Topic :: Office/Business :: Financial :: Investment
Classifier: Topic :: Software Development :: Libraries :: Python Modules
Classifier: Topic :: Scientific/Engineering :: Information Analysis
Classifier: Typing :: Typed
Classifier: Natural Language :: English
Requires-Python: >=3.11
License-File: LICENSE
Requires-Dist: grpcio-health-checking>=1.48.0
Requires-Dist: pydantic>=2.0.0
Requires-Dist: pydantic-settings>=2.0.0
Requires-Dist: python-dateutil>=2.8.0
Requires-Dist: requests>=2.28.0
Requires-Dist: tektii-strategy-protocolbuffers-python==31.1.0.1.20250811142615+36044e963970
Requires-Dist: tektii-strategy-grpc-python==1.74.0.1.20250811142615+36044e963970
Requires-Dist: tektii-broker-protocolbuffers-python==31.1.0.1.20250811144523+61bf5f68cd93
Requires-Dist: tektii-broker-grpc-python==1.74.1.1.20250811144523+61bf5f68cd93
Provides-Extra: dev
Requires-Dist: pytest>=7.0.0; extra == "dev"
Requires-Dist: pytest-cov>=4.0.0; extra == "dev"
Requires-Dist: pytest-asyncio>=0.21.0; extra == "dev"
Requires-Dist: pytest-mock>=3.10.0; extra == "dev"
Requires-Dist: pytest-benchmark>=4.0.0; extra == "dev"
Requires-Dist: pytest-xdist>=3.0.0; extra == "dev"
Requires-Dist: hypothesis>=6.0.0; extra == "dev"
Requires-Dist: factory-boy>=3.3.0; extra == "dev"
Requires-Dist: black>=23.0.0; extra == "dev"
Requires-Dist: isort>=5.12.0; extra == "dev"
Requires-Dist: mypy>=1.0.0; extra == "dev"
Requires-Dist: flake8>=6.0.0; extra == "dev"
Requires-Dist: Flake8-pyproject>=1.2.3; extra == "dev"
Requires-Dist: bandit>=1.7.0; extra == "dev"
Requires-Dist: pre-commit>=3.0.0; extra == "dev"
Requires-Dist: commitizen>=3.13.0; extra == "dev"
Requires-Dist: ipython>=8.0.0; extra == "dev"
Requires-Dist: ipdb>=0.13.0; extra == "dev"
Requires-Dist: grpcio-testing>=1.48.0; extra == "dev"
Requires-Dist: types-protobuf>=4.21.0; extra == "dev"
Requires-Dist: types-python-dateutil>=2.8.0; extra == "dev"
Requires-Dist: types-requests>=2.32.0; extra == "dev"
Requires-Dist: build>=0.10.0; extra == "dev"
Requires-Dist: twine>=4.0.0; extra == "dev"
Requires-Dist: wheel>=0.38.0; extra == "dev"
Provides-Extra: docs
Requires-Dist: sphinx>=5.0.0; extra == "docs"
Requires-Dist: sphinx-rtd-theme>=1.2.0; extra == "docs"
Requires-Dist: sphinx-autodoc-typehints>=1.22.0; extra == "docs"
Dynamic: license-file
